{
  "results": [
    {
      "name": "Thomas Moore",
      "state": "Alabama",
      "county": "Adair",
      "taxId": "29205527",
      "paymentId": "62082574",
      "amount": "386.93",
      "program": "0329458L",
      "issueDate": "02/17/2019",
      "primaryRef": "CE-9284283794",
      "dateReceived": "03/29/2019",
      "actions": [
        {
          "id": "40938420398",
          "label": "Other Agency Offset",
          "btnClass": "fsa-btn--secondary",
          "action": {
            "type": "goto",
            "val": "/demos/help/other-agency-offset2"
          }
        },
        {
          "id": "4sdfsd20398",
          "label": "Reset Payment",
          "btnClass": "fsa-btn--secondary",
          "action": {
            "type": "alert",
            "val": "Perform Reset Payment Process"
          }
        }
      ]
    },
    {
      "name": "Benjamin Allen",
      "state": "Alabama",
      "county": "Adair",
      "taxId": "93823827",
      "paymentId": "93318274",
      "amount": "430.23",
      "program": "0329458L",
      "issueDate": "11/29/2018",
      "primaryRef": "CE-9284283794",
      "dateReceived": "12/03/2018",
      "actions": [
        {
          "id": "wsdvlim420398",
          "label": "Foreign Tax Withholding",
          "btnClass": "fsa-btn--secondary"
        },
        {
          "id": "409384sdfds90fsd",
          "label": "Reset Payment",
          "btnClass": "fsa-btn--secondary"
        }
      ]
    },
    {
      "name": "Sally Matthews",
      "state": "Alabama",
      "county": "Adair",
      "taxId": "91043827",
      "paymentId": "81030274",
      "amount": "426.93",
      "program": "0329458L",
      "issueDate": "03/29/2019",
      "primaryRef": "CE-9283883794",
      "dateReceived": "03/29/2019",
      "actions": [
        {
          "id": "4sdfw09dv98",
          "label": "Prompt Pay",
          "btnClass": "fsa-btn--secondary"
        }
      ]
    },
    {
      "name": "Timothy Higginsville",
      "state": "Alabama",
      "county": "Adair",
      "taxId": "97421047",
      "paymentId": "62930074",
      "amount": "826.93",
      "program": "0329458L",
      "issueDate": "03/29/2019",
      "primaryRef": "CE-9284283794",
      "dateReceived": "03/29/2019",
      "actions": [
        {
          "id": "4sdfsfde420398",
          "label": "Other Agency Offset",
          "btnClass": "fsa-btn--secondary",
          "action": {
            "type": "goto",
            "val": "/demos/help/other-agency-offset"
          }
        }
      ]
    },
    {
      "name": "Anthony McGillis",
      "state": "Alabama",
      "county": "Adair",
      "taxId": "20205527",
      "paymentId": "80138824",
      "amount": "1010.43",
      "program": "0329458L",
      "issueDate": "03/29/2019",
      "primaryRef": "CE-9283883794",
      "dateReceived": "03/29/2019",
      "actions": [
        {
          "id": "403sdds938sde398",
          "label": "Other Agency Offset",
          "btnClass": "fsa-btn--secondary",
          "action": {
            "type": "goto",
            "val": "/demos/help/other-agency-offset"
          }
        }
      ]
    },
    {
      "name": "Pamela Furgusterson",
      "state": "Alabama",
      "county": "Adair",
      "taxId": "21185527",
      "paymentId": "94291074",
      "amount": "403.25",
      "program": "0329458L",
      "issueDate": "03/29/2019",
      "primaryRef": "CE-9284283794",
      "dateReceived": "03/29/2019",
      "actions": [
        {
          "id": "40sdfsdvsd398",
          "label": "Other Agency Offset",
          "btnClass": "fsa-btn--secondary",
          "action": {
            "type": "goto",
            "val": "/demos/help/other-agency-offset"
          }
        }
      ]
    },
    {
      "name": "Brian Hutchen",
      "state": "Alabama",
      "county": "Adair",
      "taxId": "08253327",
      "paymentId": "62938274",
      "amount": "426.93",
      "program": "0329458L",
      "issueDate": "03/29/2019",
      "primaryRef": "CE-9283888294",
      "dateReceived": "03/29/2019",
      "actions": [
        {
          "id": "4sdfw09dv98",
          "label": "Prompt Pay",
          "btnClass": "fsa-btn--secondary"
        }
      ]
    },
    {
      "name": "Sally Matthews",
      "state": "Alabama",
      "county": "Adair",
      "taxId": "29204127",
      "paymentId": "87018274",
      "amount": "2970.23",
      "program": "0329458L",
      "issueDate": "03/29/2019",
      "primaryRef": "CE-9284283794",
      "dateReceived": "03/29/2019",
      "actions": [
        {
          "id": "409384309jixvlksj",
          "label": "Other Agency Offset",
          "btnClass": "fsa-btn--secondary",
          "action": {
            "type": "goto",
            "val": "/demos/help/other-agency-offset"
          }
        }
      ]
    },
    {
      "name": "Francis Mitchell",
      "state": "Alabama",
      "county": "Adair",
      "taxId": "29205527",
      "paymentId": "82733274",
      "amount": "4122.90",
      "program": "0329458L",
      "issueDate": "03/29/2019",
      "primaryRef": "CE-9284283794",
      "dateReceived": "03/29/2019",
      "actions": [
        {
          "id": "09ulkm.soefjjlvjxe0398",
          "label": "Other Agency Offset",
          "btnClass": "fsa-btn--secondary",
          "action": {
            "type": "goto",
            "val": "/demos/help/other-agency-offset"
          }
        }
      ]
    },
    {
      "name": "Roberta Gonzolez",
      "state": "Alabama",
      "county": "Adair",
      "taxId": "93823327",
      "paymentId": "64398274",
      "amount": "3823.05",
      "program": "0329458L",
      "issueDate": "03/29/2019",
      "primaryRef": "CE-9284288294",
      "dateReceived": "03/29/2019",
      "actions": [
        {
          "id": "4sdfw09dv98",
          "label": "Prompt Pay",
          "btnClass": "fsa-btn--secondary"
        }
      ]
    },
    {
      "name": "Becky Billings",
      "state": "Alabama",
      "county": "Adair",
      "taxId": "29498727",
      "paymentId": "82003274",
      "amount": "1226.00",
      "program": "0329458L",
      "issueDate": "11/29/2018",
      "primaryRef": "CE-9284283794",
      "dateReceived": "12/03/2018",
      "actions": [
        {
          "id": "4sdfw09dv98",
          "label": "Prompt Pay",
          "btnClass": "fsa-btn--secondary"
        }
      ]
    },
    {
      "name": "Patricia Clarksworth",
      "state": "Alabama",
      "county": "Adair",
      "taxId": "29204127",
      "paymentId": "79031827",
      "amount": "400.93",
      "program": "0329458L",
      "issueDate": "03/29/2019",
      "primaryRef": "CE-9284288294",
      "dateReceived": "03/29/2019",
      "actions": [
        {
          "id": "4dsi4sdjofije8h898",
          "label": "Other Agency Offset",
          "btnClass": "fsa-btn--secondary",
          "action": {
            "type": "goto",
            "val": "/demos/help/other-agency-offset"
          }
        }
      ]
    }
  ]
}